spoils/__init__.py
spoils/_version.py
spoils/plugins/__init__.py
spoils/plugins/os_path_join.py
spoils/scripts/__init__.py
spoils-0.1.0.dist-info/licenses/LICENSE
spoils-0.1.0.dist-info/METADATA
spoils-0.1.0.dist-info/WHEEL
spoils-0.1.0.dist-info/entry_points.txt
spoils-0.1.0.dist-info/top_level.txt
spoils-0.1.0.dist-info/RECORD
