Metadata-Version: 2.4
Name: spoils
Version: 0.1.0
Summary: Multiple Processes in a Single Container
Author-email: "Bugsink B.V." <info@bugsink.com>
License-Expression: BSD-3-Clause
Project-URL: homepage, https://github.com/bugsink/spoils
Project-URL: repository, https://github.com/bugsink/spoils
Project-URL: issues, https://github.com/bugsink/spoils/issues
Classifier: Programming Language :: Python :: 3
Requires-Python: >=3.8
License-File: LICENSE
Requires-Dist: bandit
Dynamic: license-file
